Metadata-Version: 1.0
Name: filedb
Version: 0.2.3
Summary: Create a file that pretends to be a database query
Home-page: https://github.com/yhat/filedb
Author: Greg Lamp
Author-email: greg@yhathq.com
License: BSD
Platform: UNKNOWN
